MANIFEST.in
README
setup.py
bin/li
lissues/__init__.py
lissues/ws.py
lissues.egg-info/PKG-INFO
lissues.egg-info/SOURCES.txt
lissues.egg-info/dependency_links.txt
lissues.egg-info/requires.txt
lissues.egg-info/top_level.txt