Metadata-Version: 1.0
Name: lissues
Version: 0.1.0
Summary: A simple client to redmine issues tracker
Home-page: http://www.gcoop.coop
Author: Hugo Ruscitti
Author-email: hugoruscitti@gmail.com
License: UNKNOWN
Platform: UNKNOWN
Classifier: Intended Audience :: Developers
Classifier: License :: OSI Approved :: GNU Library or Lesser General Public License (LGPL)
Classifier: Natural Language :: Spanish
Classifier: Operating System :: OS Independent
Classifier: Programming Language :: Python
Classifier: Topic :: Software Development :: Libraries
